setup.py
src/fin/__init__.py
src/fin/abstract.py
src/fin/abstract_test.py
src/fin/cache.py
src/fin/cache_test.py
src/fin/color.py
src/fin/color_test.py
src/fin/config.py
src/fin/config_test.py
src/fin/contextlog.py
src/fin/contextlog_test.py
src/fin/duplex.py
src/fin/duplex_test.py
src/fin/exception.py
src/fin/module.py
src/fin/module_test.py
src/fin/patch.py
src/fin/patch_test.py
src/fin/string.py
src/fin/string_test.py
src/fin/terminal.py
src/fin/testing.py
src/fin/testing_test.py
src/fin.egg-info/PKG-INFO
src/fin.egg-info/SOURCES.txt
src/fin.egg-info/dependency_links.txt
src/fin.egg-info/top_level.txt