Metadata-Version: 1.1
Name: fin
Version: 2.1.4
Summary: A small, useful python utility library
Home-page: http://github.com/stestagg/fin
Author: Steve Stagg
Author-email: stestagg@gmail.com
License: BSD
Platform: UNKNOWN
Classifier: Development Status :: 4 - Beta
Classifier: Intended Audience :: Developers
Classifier: License :: OSI Approved :: BSD License
Classifier: Operating System :: OS Independent
Classifier: Programming Language :: Python
